imagem_processing/__init__.py
imagem_processing/processing/__init__.py
imagem_processing/processing/combination.py
imagem_processing/processing/transformation.py
imagem_processing/utils/__init__.py
imagem_processing/utils/io.py
imagem_processing/utils/plot.py
Imagem_processing_package-0.0.1.dist-info/METADATA
Imagem_processing_package-0.0.1.dist-info/WHEEL
Imagem_processing_package-0.0.1.dist-info/top_level.txt
Imagem_processing_package-0.0.1.dist-info/RECORD
