Metadata-Version: 2.1
Name: Imagem-processing-package
Version: 0.0.1
Summary: Pacote de processamentos de Imagens
Home-page: https://github.com/CABRALFARMA
Author: Marcio_Cabral
Author-email: cabralfarma@hotmail.com
License: UNKNOWN
Platform: UNKNOWN
Requires-Python: >=3.8
Requires-Dist: matplotlib
Requires-Dist: numpy
Requires-Dist: scikit-image (>=0.16.1)
